ryugraph/__init__.py
ryugraph/_ryugraph.cpython-38-x86_64-linux-gnu.so
ryugraph/async_connection.py
ryugraph/connection.py
ryugraph/constants.py
ryugraph/database.py
ryugraph/prepared_statement.py
ryugraph/py.typed
ryugraph/query_result.py
ryugraph/torch_geometric_feature_store.py
ryugraph/torch_geometric_graph_store.py
ryugraph/torch_geometric_result_converter.py
ryugraph/types.py
ryugraph-25.9.2.dist-info/LICENSE
ryugraph-25.9.2.dist-info/METADATA
ryugraph-25.9.2.dist-info/WHEEL
ryugraph-25.9.2.dist-info/top_level.txt
ryugraph-25.9.2.dist-info/RECORD
