Metadata-Version: 2.1
Name: ryugraph
Version: 25.9.2
Summary: Highly scalable, extremely fast, easy-to-use embeddable graph database
Home-page: https://github.com/predictable-labs/ryugraph
License: MIT
Project-URL: Homepage, https://ryugraph.io/
Project-URL: Documentation, https://docs.ryugraph.io/
Project-URL: Repository, https://github.com/predictable-labs/ryugraph
Project-URL: Changelog, https://github.com/predictable-labs/ryugraph/releases
Keywords: graph,database
License-File: LICENSE
